{
    "Events": [
        {
            "Date": "Wed, 02 Jan",
            "currency": "S$",
            "gst": "-",
            "id": 1,
            "image": "https://www.sgxacademy.com/wp-content/uploads/2018/10/gettyimages-607886220_super-r-01.jpg",
            "isAvailable": "Available",
            "price": "S$35",
            "title": "Technical Trend Trading: An Introduction",
            "type": "Beginner",
            "url": "https://www.sgxacademy.com/event/technical-trend-trading-an-introduction/"
        },
        {
            "Date": "Wed, 02 Jan",
            "currency": "S$",
            "gst": "-",
            "id": 2,
            "image": "https://www.sgxacademy.com/wp-content/uploads/2018/12/currency1.jpg",
            "isAvailable": "Available",
            "price": "S$35",
            "title": "2019\u4e0a\u534a\u5e74\u5168\u7403\u5e02\u573a\u5c55\u671b\u4e0e\u4e3b\u8981\u5e02\u573a\u6295\u8d44\u5f62\u52bf",
            "type": "Beginner",
            "url": "https://www.sgxacademy.com/event/2019%e4%b8%8a%e5%8d%8a%e5%b9%b4%e5%85%a8%e7%90%83%e5%b8%82%e5%9c%ba%e5%b1%95%e6%9c%9b%e4%b8%8e%e4%b8%bb%e8%a6%81%e5%b8%82%e5%9c%ba%e6%8a%95%e8%b5%84%e5%bd%a2%e5%8a%bf/"
        },
        {
            "Date": "Thu, 03 Jan",
            "currency": "S$",
            "gst": "-",
            "id": 3,
            "image": "https://www.sgxacademy.com/wp-content/uploads/2018/12/dlc.jpg",
            "isAvailable": "Available",
            "price": "S$35",
            "title": "Webinar: Capturing Market Swings with Single Stock DLCs",
            "type": "Beginner",
            "url": "https://www.sgxacademy.com/event/webinar-capturing-market-swings-with-single-stock-dlcs/"
        },
        {
            "Date": "Fri, 04 Jan",
            "currency": "S$",
            "gst": "-",
            "id": 4,
            "image": "https://www.sgxacademy.com/wp-content/uploads/2018/09/shutterstock_102523307_211x136.jpg",
            "isAvailable": "Available",
            "price": "S$35",
            "title": "A Guide To Financial Statements",
            "type": "Beginner",
            "url": "https://www.sgxacademy.com/event/a-guide-to-financial-statements/"
        },
        {
            "Date": "Mon, 07 Jan",
            "currency": "S$",
            "gst": "-",
            "id": 5,
            "image": "https://www.sgxacademy.com/wp-content/uploads/2018/09/shutterstock_122832445_211x1362.jpg",
            "isAvailable": "Available",
            "price": "S$128",
            "title": "The Key to Investing \u2013 Planning & Strategizing",
            "type": "Beginner",
            "url": "https://www.sgxacademy.com/event/the-key-to-investing-planning-strategizing-2/"
        },
        {
            "Date": "Tue, 08 Jan",
            "currency": "S$",
            "gst": "-",
            "id": 6,
            "image": "https://www.sgxacademy.com/wp-content/uploads/2018/09/currency1.jpg",
            "isAvailable": "Available",
            "price": "S$128",
            "title": "Make Trading Your Source Of Income",
            "type": "Beginner",
            "url": "https://www.sgxacademy.com/event/make-trading-your-source-of-income-5/"
        },
        {
            "Date": "Wed, 09 Jan",
            "currency": "S$",
            "gst": "-",
            "id": 7,
            "image": "https://www.sgxacademy.com/wp-content/uploads/2018/09/retail-webinar-event-image-01.jpg",
            "isAvailable": "Available",
            "price": "S$128",
            "title": "Webinar: Buying Stocks When They\u2019re On Sale!",
            "type": "Beginner",
            "url": "https://www.sgxacademy.com/event/webinar-buying-stocks-when-theyre-on-sale/"
        },
        {
            "Date": "Wed, 09 Jan",
            "currency": "S$",
            "gst": "-",
            "id": 8,
            "image": "https://www.sgxacademy.com/wp-content/uploads/2018/09/shutterstock_115798921_211x1361.jpg",
            "isAvailable": "Available",
            "price": "S$128",
            "title": "The Basics of Investing",
            "type": "Beginner",
            "url": "https://www.sgxacademy.com/event/the-basics-of-investing/"
        },
        {
            "Date": "Thu, 10 Jan",
            "currency": "S$",
            "gst": "-",
            "id": 9,
            "image": "https://www.sgxacademy.com/wp-content/uploads/2018/09/ibf-level-1-01-1.jpg",
            "isAvailable": "Available",
            "price": "S$128",
            "title": "Introduction to SGX CSP Module 3: Fundamental Analysis",
            "type": "Beginner",
            "url": "https://www.sgxacademy.com/event/introduction-to-sgx-csp-module-3-fundamental-analysis-2/"
        },
        {
            "Date": "Sat, 12 Jan",
            "currency": "S$",
            "gst": "-",
            "id": 10,
            "image": "https://www.sgxacademy.com/wp-content/uploads/2018/11/longterm.jpg",
            "isAvailable": "Available",
            "price": "S$128",
            "title": "Investing for the Long Term: Building Your Million Dollar...",
            "type": "Beginner",
            "url": "https://www.sgxacademy.com/event/investing-for-the-long-term-building-your-million-dollar-portfolio/"
        },
        {
            "Date": "Mon, 14 Jan",
            "currency": "S$",
            "gst": "-",
            "id": 11,
            "image": "https://www.sgxacademy.com/wp-content/uploads/2018/12/gettyimages-519831592_high1-1-952x579.jpg",
            "isAvailable": "Available",
            "price": "S$35",
            "title": "Effective Technical Analysis and Market Forecasting",
            "type": "Beginner",
            "url": "https://www.sgxacademy.com/event/effective-technical-analysis-and-market-forecasting/"
        },
        {
            "Date": "Tue, 15 Jan",
            "currency": "S$",
            "gst": "-",
            "id": 12,
            "image": "https://www.sgxacademy.com/wp-content/uploads/2018/09/shutterstock_102523307_211x136.jpg",
            "isAvailable": "Available",
            "price": "S$35",
            "title": "Dissecting Analyst Reports: Reading Between the Lines of a...",
            "type": "Beginner",
            "url": "https://www.sgxacademy.com/event/dissecting-analyst-reports-reading-between-the-lines-of-a-stock-call/"
        },
        {
            "Date": "Tue, 15 Jan",
            "currency": "S$",
            "gst": "-",
            "id": 13,
            "image": "https://www.sgxacademy.com/wp-content/uploads/2018/09/gettyimages-607886220_super-r-01.jpg",
            "isAvailable": "Available",
            "price": "S$35",
            "title": "Technical Trend Trading: An Introduction",
            "type": "Beginner",
            "url": "https://www.sgxacademy.com/event/technical-trend-trading-an-introduction-2/"
        },
        {
            "Date": "Wed, 16 Jan",
            "currency": "S$",
            "gst": "-",
            "id": 14,
            "image": "https://www.sgxacademy.com/wp-content/uploads/2018/12/macquarie-logo.jpg",
            "isAvailable": "Available",
            "price": "S$35",
            "title": "The Essentials of Trading Warrants",
            "type": "Beginner",
            "url": "https://www.sgxacademy.com/event/the-essentials-of-trading-warrants-2/"
        },
        {
            "Date": "Wed, 16 Jan",
            "currency": "S$",
            "gst": "-",
            "id": 15,
            "image": "https://www.sgxacademy.com/wp-content/uploads/2018/09/shutterstock_71606587_211x1364.jpg",
            "isAvailable": "Available",
            "price": "S$35",
            "title": "Introduction to Gaining a Trading Edge through Price and...",
            "type": "Beginner",
            "url": "https://www.sgxacademy.com/event/introduction-to-gaining-a-trading-edge-through-price-and-volume-action-techniques/"
        },
        {
            "Date": "Thu, 17 Jan",
            "currency": "S$",
            "gst": "-",
            "id": 16,
            "image": "https://www.sgxacademy.com/wp-content/uploads/2018/09/currency1.jpg",
            "isAvailable": "Available",
            "price": "S$35",
            "title": "Introduction to Futures and its Benefits to Retail Traders",
            "type": "Beginner",
            "url": "https://www.sgxacademy.com/event/introduction-to-futures-and-its-benefits-to-retail-traders-3/"
        },
        {
            "Date": "Sat, 19 Jan",
            "currency": "S$",
            "gst": "-",
            "id": 17,
            "image": "https://www.sgxacademy.com/wp-content/uploads/2018/09/shutterstock_102523307_211x136.jpg",
            "isAvailable": "Available",
            "price": "S$549",
            "title": "Analysing Financial Statements: How to Interpret Financial Reports",
            "type": "Intermediate",
            "url": "https://www.sgxacademy.com/event/analysing-financial-statements-how-to-interpret-financial-reports/"
        },
        {
            "Date": "Sat, 19 Jan",
            "currency": "S$",
            "gst": "-",
            "id": 18,
            "image": "https://www.sgxacademy.com/wp-content/uploads/2018/09/ibf-level-1-01-2.jpg",
            "isAvailable": "Available",
            "price": "S$310",
            "title": "SGX CSP Module 3: Fundamental Analysis",
            "type": "Professional",
            "url": "https://www.sgxacademy.com/event/sgx-csp-module-3-fundamental-analysis-2/"
        },
        {
            "Date": "Mon, 21 Jan",
            "currency": "S$",
            "gst": "-",
            "id": 19,
            "image": "https://www.sgxacademy.com/wp-content/uploads/2018/09/shutterstock_68191825_211x1361.jpg",
            "isAvailable": "Available",
            "price": "S$35",
            "title": "Bull & Bear Investment Strategies",
            "type": "Beginner",
            "url": "https://www.sgxacademy.com/event/bull-bear-investment-strategies/"
        },
        {
            "Date": "Tue, 22 Jan",
            "currency": "S$",
            "gst": "-",
            "id": 20,
            "image": "https://www.sgxacademy.com/wp-content/uploads/2018/09/currency1.jpg",
            "isAvailable": "Available",
            "price": "S$2,400",
            "title": "Make Trading Your Source Of Income",
            "type": "Beginner",
            "url": "https://www.sgxacademy.com/event/make-trading-your-source-of-income-6/"
        },
        {
            "Date": "Tue, 22 Jan",
            "currency": "S$",
            "gst": "-",
            "id": 21,
            "image": "https://www.sgxacademy.com/wp-content/uploads/2018/11/longterm.jpg",
            "isAvailable": "Available",
            "price": "S$2,400",
            "title": "Steady Steps To Grow Your Savings",
            "type": "Beginner",
            "url": "https://www.sgxacademy.com/event/steady-steps-to-grow-your-savings/"
        },
        {
            "Date": "Wed, 23 Jan",
            "currency": "S$",
            "gst": "-",
            "id": 22,
            "image": "https://www.sgxacademy.com/wp-content/uploads/2018/12/currency1.jpg",
            "isAvailable": "Available",
            "price": "S$2,400",
            "title": "2019\u4e0a\u534a\u5e74\u5168\u7403\u5e02\u573a\u5c55\u671b\u4e0e\u4e3b\u8981\u5e02\u573a\u6295\u8d44\u5f62\u52bf",
            "type": "Beginner",
            "url": "https://www.sgxacademy.com/event/2019%e4%b8%8a%e5%8d%8a%e5%b9%b4%e5%85%a8%e7%90%83%e5%b8%82%e5%9c%ba%e5%b1%95%e6%9c%9b%e4%b8%8e%e4%b8%bb%e8%a6%81%e5%b8%82%e5%9c%ba%e6%8a%95%e8%b5%84%e5%bd%a2%e5%8a%bf-2/"
        },
        {
            "Date": "Sat, 26 Jan",
            "currency": "S$",
            "gst": "-",
            "id": 23,
            "image": "https://www.sgxacademy.com/wp-content/uploads/2018/09/currency1.jpg",
            "isAvailable": "Available",
            "price": "S$2,400",
            "title": "Essentials of Professional Futures Trading with TA",
            "type": "Professional",
            "url": "https://www.sgxacademy.com/event/essentials-of-professional-futures-trading-with-ta-2/"
        },
        {
            "Date": "Sat, 26 Jan",
            "currency": "S$",
            "gst": "-",
            "id": 24,
            "image": "https://www.sgxacademy.com/wp-content/uploads/2018/09/gettyimages-607886220_super-r-01.jpg",
            "isAvailable": "Available",
            "price": "S$988",
            "title": "Technical Trend Trading: The Complete System",
            "type": "Intermediate",
            "url": "https://www.sgxacademy.com/event/technical-trend-trading-the-complete-system-2/"
        },
        {
            "Date": "Tue, 29 Jan",
            "currency": "S$",
            "gst": "-",
            "id": 25,
            "image": "https://www.sgxacademy.com/wp-content/uploads/2018/09/equity1.jpg",
            "isAvailable": "Available",
            "price": "S$128",
            "title": "Basics of Investing Plus \u2013 Foundations of REIT Investing",
            "type": "Beginner",
            "url": "https://www.sgxacademy.com/event/basics-of-investing-plus-foundations-of-reit-investing-2/"
        },
        {
            "Date": "Thu, 31 Jan",
            "currency": "S$",
            "gst": "-",
            "id": 26,
            "image": "https://www.sgxacademy.com/wp-content/uploads/2018/09/shutterstock_146573270.jpg",
            "isAvailable": "Available",
            "price": "S$35",
            "title": "Basics of Creating a Secondary Income Stream",
            "type": "Beginner",
            "url": "https://www.sgxacademy.com/event/basics-of-creating-a-secondary-income-stream/"
        },
        {
            "Date": "Mon, 11 Feb",
            "currency": "S$",
            "gst": "-",
            "id": 27,
            "image": "https://www.sgxacademy.com/wp-content/uploads/2018/09/shutterstock_71606587_211x1364.jpg",
            "isAvailable": "Available",
            "price": "S$35",
            "title": "Introduction to Gaining a Trading Edge through Price and...",
            "type": "Beginner",
            "url": "https://www.sgxacademy.com/event/introduction-to-gaining-a-trading-edge-through-price-and-volume-action-techniques-2/"
        },
        {
            "Date": "Mon, 11 Feb",
            "currency": "S$",
            "gst": "-",
            "id": 28,
            "image": "https://www.sgxacademy.com/wp-content/uploads/2018/12/derivatives2.jpg",
            "isAvailable": "Available",
            "price": "S$35",
            "title": "A Guide to Derivatives Trading",
            "type": "Beginner",
            "url": "https://www.sgxacademy.com/event/a-guide-to-derivatives-trading/"
        },
        {
            "Date": "Tue, 12 Feb",
            "currency": "S$",
            "gst": "-",
            "id": 29,
            "image": "https://www.sgxacademy.com/wp-content/uploads/2018/09/currency.jpg",
            "isAvailable": "Available",
            "price": "S$35",
            "title": "Make Trading Your Source Of Income",
            "type": "Beginner",
            "url": "https://www.sgxacademy.com/event/make-trading-your-source-of-income-7/"
        },
        {
            "Date": "Wed, 13 Feb",
            "currency": "S$",
            "gst": "-",
            "id": 30,
            "image": "https://www.sgxacademy.com/wp-content/uploads/2018/09/retail-webinar-event-image.jpg",
            "isAvailable": "Available",
            "price": "S$35",
            "title": "Webinar: How to Read and Dissect an Annual Report...",
            "type": "Beginner",
            "url": "https://www.sgxacademy.com/event/webinar-how-to-read-and-dissect-an-annual-report-in-5-easy-steps/"
        },
        {
            "Date": "Thu, 14 Feb",
            "currency": "S$",
            "gst": "-",
            "id": 31,
            "image": "https://www.sgxacademy.com/wp-content/uploads/2018/09/shutterstock_102523307_211x136.jpg",
            "isAvailable": "Available",
            "price": "S$35",
            "title": "A Guide To Financial Statements",
            "type": "Beginner",
            "url": "https://www.sgxacademy.com/event/a-guide-to-financial-statements-2/"
        },
        {
            "Date": "Thu, 14 Feb",
            "gst": "-",
            "id": 32,
            "image": "https://www.sgxacademy.com/wp-content/uploads/2018/09/shutterstock_122832445_211x136-copy.jpg",
            "isAvailable": "Available",
            "price": "FOC",
            "title": "Introduction to Applied Value Investing",
            "type": "Beginner",
            "url": "https://www.sgxacademy.com/event/introduction-to-applied-value-investing-2/"
        },
        {
            "Date": "Fri, 15 Feb",
            "currency": "S$",
            "gst": "-",
            "id": 33,
            "image": "https://www.sgxacademy.com/wp-content/uploads/2018/09/shutterstock_146573270.jpg",
            "isAvailable": "Available",
            "price": "S$528",
            "title": "Basics of Creating a Secondary Income Stream",
            "type": "Beginner",
            "url": "https://www.sgxacademy.com/event/basics-of-creating-a-secondary-income-stream-2/"
        },
        {
            "Date": "Sat, 16 Feb",
            "currency": "S$",
            "gst": "-",
            "id": 34,
            "image": "https://www.sgxacademy.com/wp-content/uploads/2018/12/shutterstock_134379221.jpg",
            "isAvailable": "Available",
            "price": "S$528",
            "title": "\u57fa\u672c\u9762\u5206\u6790\u6295\u8d44\u7b56\u7565\u8bfe\u7a0b (\u4e2d\u7ea7)",
            "type": "Intermediate",
            "url": "https://www.sgxacademy.com/event/%e5%9f%ba%e6%9c%ac%e9%9d%a2%e5%88%86%e6%9e%90%e6%8a%95%e8%b5%84%e7%ad%96%e7%95%a5%e8%af%be%e7%a8%8b-%e4%b8%ad%e7%ba%a7/"
        },
        {
            "Date": "Sat, 16 Feb",
            "currency": "S$",
            "gst": "-",
            "id": 35,
            "image": "https://www.sgxacademy.com/wp-content/uploads/2018/09/shutterstock_102523307_211x136.jpg",
            "isAvailable": "Available",
            "price": "S$549",
            "title": "Financial Analysis Techniques: How to Find the Hidden Information...",
            "type": "Intermediate",
            "url": "https://www.sgxacademy.com/event/financial-analysis-techniques-how-to-find-the-hidden-information-in-financial-reports-2/"
        },
        {
            "Date": "Mon, 18 Feb",
            "currency": "S$",
            "gst": "-",
            "id": 36,
            "image": "https://www.sgxacademy.com/wp-content/uploads/2018/09/shutterstock_122832445_211x1362.jpg",
            "isAvailable": "Available",
            "price": "S$35",
            "title": "The Key to Investing \u2013 Planning & Strategizing",
            "type": "Beginner",
            "url": "https://www.sgxacademy.com/event/the-key-to-investing-planning-strategizing-3/"
        },
        {
            "Date": "Tue, 19 Feb",
            "currency": "S$",
            "gst": "-",
            "id": 37,
            "image": "https://www.sgxacademy.com/wp-content/uploads/2018/09/currency1.jpg",
            "isAvailable": "Available",
            "price": "S$35",
            "title": "Introduction to Futures and its Benefits to Retail Traders",
            "type": "Beginner",
            "url": "https://www.sgxacademy.com/event/introduction-to-futures-and-its-benefits-to-retail-traders-4/"
        },
        {
            "Date": "Wed, 20 Feb",
            "currency": "S$",
            "gst": "-",
            "id": 38,
            "image": "https://www.sgxacademy.com/wp-content/uploads/2018/09/shutterstock_122832445_211x136-copy.jpg",
            "isAvailable": "Available",
            "price": "S$35",
            "title": "The Search for Value (Applied Value Investing)",
            "type": "Beginner",
            "url": "https://www.sgxacademy.com/event/the-search-for-value-applied-value-investing-2/"
        },
        {
            "Date": "Wed, 20 Feb",
            "currency": "S$",
            "gst": "-",
            "id": 39,
            "image": "https://www.sgxacademy.com/wp-content/uploads/2018/09/shutterstock_134379248_211x1363.jpg",
            "isAvailable": "Available",
            "price": "S$428",
            "title": "Margin on REITs \u2013 Higher Returns, Higher Risks!",
            "type": "Intermediate",
            "url": "https://www.sgxacademy.com/event/margin-on-reits-higher-returns-higher-risks-2/"
        },
        {
            "Date": "Thu, 21 Feb",
            "currency": "S$",
            "gst": "-",
            "id": 40,
            "image": "https://www.sgxacademy.com/wp-content/uploads/2018/09/gettyimages-519831592_high-952x579.jpg",
            "isAvailable": "Available",
            "price": "S$35",
            "title": "Effective Technical Analysis and Market Forecasting",
            "type": "Beginner",
            "url": "https://www.sgxacademy.com/event/effective-technical-analysis-and-market-forecasting-2/"
        },
        {
            "Date": "Fri, 22 Feb",
            "currency": "S$",
            "gst": "-",
            "id": 41,
            "image": "https://www.sgxacademy.com/wp-content/uploads/2018/09/shutterstock_146573270.jpg",
            "isAvailable": "Available",
            "price": "S$698",
            "title": "Create a Secondary Income Stream \u2013 Through Long Term...",
            "type": "Intermediate",
            "url": "https://www.sgxacademy.com/event/create-a-secondary-income-stream-through-long-term-share-investing/"
        },
        {
            "Date": "Fri, 22 Feb",
            "currency": "S$",
            "gst": "-",
            "id": 42,
            "image": "https://www.sgxacademy.com/wp-content/uploads/2018/09/shutterstock_115798921_211x1361.jpg",
            "isAvailable": "Available",
            "price": "S$128",
            "title": "The Basics of Investing",
            "type": "Beginner",
            "url": "https://www.sgxacademy.com/event/the-basics-of-investing-3/"
        },
        {
            "Date": "Sat, 23 Feb",
            "currency": "S$",
            "gst": "-",
            "id": 43,
            "image": "https://www.sgxacademy.com/wp-content/uploads/2018/12/finance-management.jpg",
            "isAvailable": "Available",
            "price": "S$128",
            "title": "Basics of Investing Plus \u2013 Building Blocks for Value...",
            "type": "Beginner",
            "url": "https://www.sgxacademy.com/event/basics-of-investing-plus-building-blocks-for-value-investing/"
        },
        {
            "Date": "Sat, 23 Feb",
            "currency": "S$",
            "gst": "-",
            "id": 44,
            "image": "https://www.sgxacademy.com/wp-content/uploads/2018/09/currency.jpg",
            "isAvailable": "Available",
            "price": "S$2,400",
            "title": "Essentials of Professional Futures Trading with TA",
            "type": "Professional",
            "url": "https://www.sgxacademy.com/event/essentials-of-professional-futures-trading-with-ta-4/"
        },
        {
            "Date": "Sat, 23 Feb",
            "currency": "S$",
            "gst": "-",
            "id": 45,
            "image": "https://www.sgxacademy.com/wp-content/uploads/2018/09/shutterstock_102523307_211x136.jpg",
            "isAvailable": "Available",
            "price": "S$200",
            "title": "Investors\u2019 Roadmap: Taking Control of Your Own Investments",
            "type": "Intermediate",
            "url": "https://www.sgxacademy.com/event/investors-roadmap-taking-control-of-your-own-investments-2/"
        },
        {
            "Date": "Mon, 25 Feb",
            "currency": "S$",
            "gst": "-",
            "id": 46,
            "image": "https://www.sgxacademy.com/wp-content/uploads/2018/09/gettyimages-519831592_high-952x579.jpg",
            "isAvailable": "Available",
            "price": "S$35",
            "title": "Introduction to Trading with Candlesticks",
            "type": "Beginner",
            "url": "https://www.sgxacademy.com/event/introduction-to-trading-with-candlesticks-2/"
        },
        {
            "Date": "Tue, 26 Feb",
            "currency": "S$",
            "gst": "-",
            "id": 47,
            "image": "https://www.sgxacademy.com/wp-content/uploads/2018/09/currency1.jpg",
            "isAvailable": "Available",
            "price": "S$35",
            "title": "Make Trading Your Source Of Income",
            "type": "Beginner",
            "url": "https://www.sgxacademy.com/event/make-trading-your-source-of-income-10/"
        },
        {
            "Date": "Thu, 28 Feb",
            "currency": "S$",
            "gst": "-",
            "id": 48,
            "image": "https://www.sgxacademy.com/wp-content/uploads/2018/09/shutterstock_102553814_211x1361.jpg",
            "isAvailable": "Available",
            "price": "S$35",
            "title": "Exploring Technical Analysis \u2013 How TA Can Work For...",
            "type": "Beginner",
            "url": "https://www.sgxacademy.com/event/exploring-technical-analysis-how-ta-can-work-for-you/"
        },
        {
            "Date": "Sat, 02 Mar",
            "currency": "S$",
            "gst": "-",
            "id": 49,
            "image": "https://www.sgxacademy.com/wp-content/uploads/2018/09/shutterstock_122832445_211x136.jpg",
            "isAvailable": "Available",
            "price": "S$250",
            "title": "Invest & Trade with Precision \u2013 Precision Market Entry...",
            "type": "Intermediate",
            "url": "https://www.sgxacademy.com/event/invest-trade-with-precision-precision-market-entry-strategy-2/"
        },
        {
            "Date": "Mon, 04 Mar",
            "currency": "S$",
            "gst": "-",
            "id": 50,
            "image": "https://www.sgxacademy.com/wp-content/uploads/2018/09/shutterstock_143024863_211x1361.jpg",
            "isAvailable": "Available",
            "price": "S$35",
            "title": "Easy-to-Apply Investment Strategies without Complicated Analysis",
            "type": "Beginner",
            "url": "https://www.sgxacademy.com/event/easy-to-apply-investment-strategies-without-complicated-analysis/"
        },
        {
            "Date": "Tue, 05 Mar",
            "currency": "S$",
            "gst": "-",
            "id": 51,
            "image": "https://www.sgxacademy.com/wp-content/uploads/2018/09/currency1.jpg",
            "isAvailable": "Available",
            "price": "S$35",
            "title": "Make Trading Your Source Of Income",
            "type": "Beginner",
            "url": "https://www.sgxacademy.com/event/make-trading-your-source-of-income-12/"
        },
        {
            "Date": "Wed, 06 Mar",
            "currency": "S$",
            "gst": "-",
            "id": 52,
            "image": "https://www.sgxacademy.com/wp-content/uploads/2018/09/retail-webinar-event-image.jpg",
            "isAvailable": "Available",
            "price": "S$35",
            "title": "Webinar: Build A Dividend Portfolio",
            "type": "Beginner",
            "url": "https://www.sgxacademy.com/event/webinar-build-a-dividend-protfolio/"
        },
        {
            "Date": "Thu, 07 Mar",
            "currency": "S$",
            "gst": "-",
            "id": 53,
            "image": "https://www.sgxacademy.com/wp-content/uploads/2018/09/gettyimages-519831592_high-952x579.jpg",
            "isAvailable": "Available",
            "price": "S$35",
            "title": "Introduction to Richard Wyckoff Method",
            "type": "Beginner",
            "url": "https://www.sgxacademy.com/event/introduction-to-richard-wyckoff-method/"
        },
        {
            "Date": "Tue, 12 Mar",
            "currency": "S$",
            "gst": "-",
            "id": 54,
            "image": "https://www.sgxacademy.com/wp-content/uploads/2018/11/dbsw-01.jpg",
            "isAvailable": "Available",
            "price": "S$35",
            "title": "Value Investing: Being The First Few At Each GSS",
            "type": "Beginner",
            "url": "https://www.sgxacademy.com/event/value-investing-being-the-first-few-at-each-gss/"
        },
        {
            "Date": "Tue, 12 Mar",
            "currency": "S$",
            "gst": "-",
            "id": 55,
            "image": "https://www.sgxacademy.com/wp-content/uploads/2018/09/currency1.jpg",
            "isAvailable": "Available",
            "price": "S$35",
            "title": "Make Trading Your Source Of Income",
            "type": "Beginner",
            "url": "https://www.sgxacademy.com/event/make-trading-your-source-of-income-11/"
        },
        {
            "Date": "Wed, 13 Mar",
            "currency": "S$",
            "gst": "-",
            "id": 56,
            "image": "https://www.sgxacademy.com/wp-content/uploads/2018/09/equity.jpg",
            "isAvailable": "Available",
            "price": "S$35",
            "title": "A Guide to Property Stocks",
            "type": "Beginner",
            "url": "https://www.sgxacademy.com/event/a-guide-to-property-stocks/"
        },
        {
            "Date": "Thu, 14 Mar",
            "currency": "S$",
            "gst": "-",
            "id": 57,
            "image": "https://www.sgxacademy.com/wp-content/uploads/2018/09/gettyimages-519831592_high-952x579.jpg",
            "isAvailable": "Available",
            "price": "S$35",
            "title": "Introduction to Trading with Candlesticks",
            "type": "Beginner",
            "url": "https://www.sgxacademy.com/event/introduction-to-trading-with-candlesticks-3/"
        },
        {
            "Date": "Sat, 16 Mar",
            "currency": "S$",
            "gst": "-",
            "id": 58,
            "image": "https://www.sgxacademy.com/wp-content/uploads/2018/12/shutterstock_77559352.jpg",
            "isAvailable": "Available",
            "price": "S$528",
            "title": "\u6280\u672f\u9762\u5206\u6790\u6295\u8d44\u7b56\u7565\u8bfe\u7a0b(\u4e2d\u7ea7)",
            "type": "Intermediate",
            "url": "https://www.sgxacademy.com/event/%e6%8a%80%e6%9c%af%e9%9d%a2%e5%88%86%e6%9e%90%e6%8a%95%e8%b5%84%e7%ad%96%e7%95%a5%e8%af%be%e7%a8%8b%e4%b8%ad%e7%ba%a7/"
        },
        {
            "Date": "Wed, 20 Mar",
            "currency": "S$",
            "gst": "-",
            "id": 59,
            "image": "https://www.sgxacademy.com/wp-content/uploads/2018/09/currency1.jpg",
            "isAvailable": "Available",
            "price": "S$35",
            "title": "Introduction to Futures and its Benefits to Retail Traders",
            "type": "Beginner",
            "url": "https://www.sgxacademy.com/event/introduction-to-futures-and-its-benefits-to-retail-traders-6/"
        },
        {
            "Date": "Thu, 21 Mar",
            "currency": "S$",
            "gst": "-",
            "id": 60,
            "image": "https://www.sgxacademy.com/wp-content/uploads/2018/09/shutterstock_102523307_211x136.jpg",
            "isAvailable": "Available",
            "price": "S$35",
            "title": "Navigating IPOs: An Essential Guide",
            "type": "Beginner",
            "url": "https://www.sgxacademy.com/event/navigating-ipos-an-essential-guide-2/"
        },
        {
            "Date": "Sat, 23 Mar",
            "currency": "S$",
            "gst": "-",
            "id": 61,
            "image": "https://www.sgxacademy.com/wp-content/uploads/2018/09/currency1.jpg",
            "isAvailable": "Available",
            "price": "S$2,400",
            "title": "Essentials of Professional Futures Trading with TA",
            "type": "Professional",
            "url": "https://www.sgxacademy.com/event/essentials-of-professional-futures-trading-with-ta-5/"
        },
        {
            "Date": "Sat, 23 Mar",
            "currency": "S$",
            "gst": "-",
            "id": 62,
            "image": "https://www.sgxacademy.com/wp-content/uploads/2018/09/shutterstock_134379254_211x136.jpg",
            "isAvailable": "Available",
            "price": "S$1,080",
            "title": "Applied Value Investing Workshop",
            "type": "Intermediate",
            "url": "https://www.sgxacademy.com/event/applied-value-investing-workshop-2/"
        },
        {
            "Date": "Mon, 25 Mar",
            "currency": "S$",
            "gst": "-",
            "id": 63,
            "image": "https://www.sgxacademy.com/wp-content/uploads/2018/09/shutterstock_68191825_211x1361.jpg",
            "isAvailable": "Available",
            "price": "S$800",
            "title": "Short Term Trading Strategies",
            "type": "Professional",
            "url": "https://www.sgxacademy.com/event/short-term-trading-strategies-2/"
        },
        {
            "Date": "Thu, 28 Mar",
            "currency": "S$",
            "gst": "-",
            "id": 64,
            "image": "https://www.sgxacademy.com/wp-content/uploads/2018/12/shutterstock_77384059.jpg",
            "isAvailable": "Available",
            "price": "S$35",
            "title": "Building Your Retirement Fund Through Stock Investment",
            "type": "Beginner",
            "url": "https://www.sgxacademy.com/event/building-your-retirement-fund-through-stock-investment/"
        },
        {
            "Date": "Sat, 30 Mar",
            "currency": "S$",
            "gst": "-",
            "id": 65,
            "image": "https://www.sgxacademy.com/wp-content/uploads/2018/09/gettyimages-519831592_high-952x579.jpg",
            "isAvailable": "Available",
            "price": "S$799",
            "title": "Richard Wyckoff Method for Trading the Markets",
            "type": "Intermediate",
            "url": "https://www.sgxacademy.com/event/richard-wyckoff-method-for-trading-the-markets/"
        },
        {
            "Date": "Sat, 30 Mar",
            "currency": "S$",
            "gst": "-",
            "id": 66,
            "image": "https://www.sgxacademy.com/wp-content/uploads/2018/11/dbsw-01.jpg",
            "isAvailable": "Available",
            "price": "S$128",
            "title": "The Women\u2019s Guide to Value Investing",
            "type": "Beginner",
            "url": "https://www.sgxacademy.com/event/the-womens-guide-to-value-investing/"
        },
        {
            "Date": "Tue, 02 Apr",
            "currency": "S$",
            "gst": "-",
            "id": 67,
            "image": "https://www.sgxacademy.com/wp-content/uploads/2018/09/currency1.jpg",
            "isAvailable": "Available",
            "price": "S$35",
            "title": "Make Trading Your Source Of Income",
            "type": "Beginner",
            "url": "https://www.sgxacademy.com/event/make-trading-your-source-of-income-9/"
        },
        {
            "Date": "Wed, 03 Apr",
            "currency": "S$",
            "gst": "-",
            "id": 68,
            "image": "https://www.sgxacademy.com/wp-content/uploads/2018/09/retail-webinar-event-image.jpg",
            "isAvailable": "Available",
            "price": "S$35",
            "title": "Webinar: Rebalancing Your Portfolio",
            "type": "Beginner",
            "url": "https://www.sgxacademy.com/event/webinar-rebalancing-your-portfolio/"
        },
        {
            "Date": "Thu, 04 Apr",
            "currency": "S$",
            "gst": "-",
            "id": 69,
            "image": "https://www.sgxacademy.com/wp-content/uploads/2018/09/gettyimages-519831592_high-952x579.jpg",
            "isAvailable": "Available",
            "price": "S$35",
            "title": "Introduction to Trading with Candlesticks",
            "type": "Beginner",
            "url": "https://www.sgxacademy.com/event/introduction-to-trading-with-candlesticks/"
        },
        {
            "Date": "Sat, 13 Apr",
            "currency": "S$",
            "gst": "-",
            "id": 70,
            "image": "https://www.sgxacademy.com/wp-content/uploads/2018/09/shutterstock_122832445_211x136-copy.jpg",
            "isAvailable": "Available",
            "price": "S$428",
            "title": "Investing Techniques for Capital Gain",
            "type": "Intermediate",
            "url": "https://www.sgxacademy.com/event/investing-techniques-for-capital-gain-2/"
        },
        {
            "Date": "Sat, 13 Apr",
            "currency": "S$",
            "gst": "-",
            "id": 71,
            "image": "https://www.sgxacademy.com/wp-content/uploads/2018/09/shutterstock_71606587_211x1364.jpg",
            "isAvailable": "Available",
            "price": "S$328",
            "title": "Candlestick and Technical Analysis Charting Techniques",
            "type": "Intermediate",
            "url": "https://www.sgxacademy.com/event/candlestick-and-technical-analysis-charting-techniques/"
        },
        {
            "Date": "Tue, 16 Apr",
            "currency": "S$",
            "gst": "-",
            "id": 72,
            "image": "https://www.sgxacademy.com/wp-content/uploads/2018/09/currency1.jpg",
            "isAvailable": "Available",
            "price": "S$2,400",
            "title": "Make Trading Your Source Of Income",
            "type": "Beginner",
            "url": "https://www.sgxacademy.com/event/make-trading-your-source-of-income-8/"
        },
        {
            "Date": "Sat, 20 Apr",
            "currency": "S$",
            "gst": "-",
            "id": 73,
            "image": "https://www.sgxacademy.com/wp-content/uploads/2018/09/currency1.jpg",
            "isAvailable": "Available",
            "price": "S$2,400",
            "title": "Essentials of Professional Futures Trading with TA",
            "type": "Professional",
            "url": "https://www.sgxacademy.com/event/essentials-of-professional-futures-trading-with-ta-3/"
        },
        {
            "Date": "Tue, 23 Apr",
            "currency": "S$",
            "gst": "-",
            "id": 74,
            "image": "https://www.sgxacademy.com/wp-content/uploads/2018/09/currency1.jpg",
            "isAvailable": "Available",
            "price": "S$35",
            "title": "Introduction to Futures and its Benefits to Retail Traders",
            "type": "Beginner",
            "url": "https://www.sgxacademy.com/event/introduction-to-futures-and-its-benefits-to-retail-traders-5/"
        },
        {
            "Date": "Wed, 24 Apr",
            "currency": "S$",
            "gst": "-",
            "id": 75,
            "image": "https://www.sgxacademy.com/wp-content/uploads/2018/09/equity1.jpg",
            "isAvailable": "Available",
            "price": "S$128",
            "title": "Basics of Investing Plus \u2013 Foundations of REIT Investing",
            "type": "Beginner",
            "url": "https://www.sgxacademy.com/event/basics-of-investing-plus-foundations-of-reit-investing-3/"
        },
        {
            "Date": "Tue, 30 Apr",
            "currency": "S$",
            "gst": "-",
            "id": 76,
            "image": "https://www.sgxacademy.com/wp-content/uploads/2018/09/shutterstock_102523307_211x136.jpg",
            "isAvailable": "Available",
            "price": "S$160",
            "title": "Interest Calculations, Time Value of Money, NPV & IRR",
            "type": "Beginner",
            "url": "https://www.sgxacademy.com/event/interest-calculations-time-value-of-money-npv-irr-3/"
        },
        {
            "Date": "Tue, 30 Apr",
            "currency": "S$",
            "gst": "-",
            "id": 77,
            "image": "https://www.sgxacademy.com/wp-content/uploads/2018/09/shutterstock_146573270.jpg",
            "isAvailable": "Available",
            "price": "S$160",
            "title": "Basics of Creating a Secondary Income Stream",
            "type": "Beginner",
            "url": "https://www.sgxacademy.com/event/basics-of-creating-a-secondary-income-stream-3/"
        },
        {
            "Date": "Thu, 02 May",
            "currency": "S$",
            "gst": "-",
            "id": 78,
            "image": "https://www.sgxacademy.com/wp-content/uploads/2018/09/retail-webinar-event-image.jpg",
            "isAvailable": "Available",
            "price": "S$160",
            "title": "Webinar: Realising the Value of Stocks",
            "type": "Beginner",
            "url": "https://www.sgxacademy.com/event/webinar-realising-the-value-of-stocks/"
        },
        {
            "currency": "S$",
            "gst": "-",
            "id": 79,
            "image": "https://www.sgxacademy.com/wp-content/uploads/2018/09/shutterstock_102553814_211x1361.jpg",
            "isAvailable": "Available",
            "price": "S$160",
            "title": "Financial Crisis & Introduction to Technical Analysis",
            "type": "Beginner",
            "url": "https://www.sgxacademy.com/event/financial-crisis-introduction-to-technical-analysis/"
        },
        {
            "currency": "S$",
            "gst": "-",
            "id": 80,
            "image": "https://www.sgxacademy.com/wp-content/uploads/2018/09/portfolio1.jpg",
            "isAvailable": "Available",
            "price": "S$160",
            "title": "Strategic and Tactical Asset Allocation",
            "type": "Intermediate",
            "url": "https://www.sgxacademy.com/event/strategic-and-tactical-asset-allocation/"
        },
        {
            "currency": "S$",
            "gst": "-",
            "id": 81,
            "image": "https://www.sgxacademy.com/wp-content/uploads/2018/09/corporate-finance1.jpg",
            "isAvailable": "Available",
            "price": "S$160",
            "title": "Role of a Custodian & Corporate Actions",
            "type": "Beginner",
            "url": "https://www.sgxacademy.com/event/role-of-a-custodian-corporate-actions-2/"
        },
        {
            "currency": "S$",
            "gst": "-",
            "id": 82,
            "image": "https://www.sgxacademy.com/wp-content/uploads/2018/09/bonds1.jpg",
            "isAvailable": "Available",
            "price": "S$160",
            "title": "Introduction to Bonds, Prices, Yields & Strategies",
            "type": "Intermediate",
            "url": "https://www.sgxacademy.com/event/introduction-to-bonds-prices-yields-strategies/"
        },
        {
            "currency": "S$",
            "gst": "-",
            "id": 83,
            "image": "https://www.sgxacademy.com/wp-content/uploads/2018/11/211x136.jpg",
            "isAvailable": "Available",
            "price": "S$160",
            "title": "Equities, Algorithmic & High Frequency Trading",
            "type": "Beginner",
            "url": "https://www.sgxacademy.com/event/equities-algorithmic-high-frequency-trading/"
        },
        {
            "currency": "S$",
            "gst": "-",
            "id": 84,
            "image": "https://www.sgxacademy.com/wp-content/uploads/2018/09/shutterstock_102553814_211x1361.jpg",
            "isAvailable": "Available",
            "price": "S$160",
            "title": "Technical Analysis Strategies",
            "type": "Beginner",
            "url": "https://www.sgxacademy.com/event/technical-analysis-strategies/"
        },
        {
            "currency": "S$",
            "gst": "-",
            "id": 85,
            "image": "https://www.sgxacademy.com/wp-content/uploads/2018/11/211x136.jpg",
            "isAvailable": "Available",
            "price": "S$160",
            "title": "Fixed Income Duration, Convexity and Credit Risk",
            "type": "Intermediate",
            "url": "https://www.sgxacademy.com/event/fixed-income-duration-convexity-and-credit-risk/"
        },
        {
            "currency": "S$",
            "gst": "-",
            "id": 86,
            "image": "https://www.sgxacademy.com/wp-content/uploads/2018/09/shutterstock_79462060_211x1361.jpg",
            "isAvailable": "Available",
            "price": "S$160",
            "title": "Forwards & Futures \u2013 Introduction, Pricing & Trading",
            "type": "Beginner",
            "url": "https://www.sgxacademy.com/event/forwards-futures-introduction-pricing-trading/"
        },
        {
            "currency": "S$",
            "gst": "-",
            "id": 87,
            "image": "https://www.sgxacademy.com/wp-content/uploads/2018/09/shutterstock_133812953_211x1361.jpg",
            "isAvailable": "Available",
            "price": "S$160",
            "title": "Exotic Options and Trading Strategies",
            "type": "Intermediate",
            "url": "https://www.sgxacademy.com/event/exotic-options-and-trading-strategies-2/"
        },
        {
            "currency": "S$",
            "gst": "-",
            "id": 88,
            "image": "https://www.sgxacademy.com/wp-content/uploads/2018/09/shutterstock_114054154_211x1361.jpg",
            "isAvailable": "Available",
            "price": "S$160",
            "title": "Private Wealth Management I",
            "type": "Beginner",
            "url": "https://www.sgxacademy.com/event/private-wealth-management-i-2/"
        },
        {
            "currency": "S$",
            "gst": "-",
            "id": 89,
            "image": "https://www.sgxacademy.com/wp-content/uploads/2018/09/corporate-finance1.jpg",
            "isAvailable": "Available",
            "price": "S$160",
            "title": "Corporate Valuation \u2013 Trading, Transaction Comparables & Merger Analysis",
            "type": "Intermediate",
            "url": "https://www.sgxacademy.com/event/corporate-valuation-trading-transaction-comparables-merger-analysis-2/"
        },
        {
            "currency": "S$",
            "gst": "-",
            "id": 90,
            "image": "https://www.sgxacademy.com/wp-content/uploads/2018/09/shutterstock_114054154_211x1361.jpg",
            "isAvailable": "Available",
            "price": "S$160",
            "title": "Private Wealth Management II",
            "type": "Beginner",
            "url": "https://www.sgxacademy.com/event/private-wealth-management-ii/"
        },
        {
            "currency": "S$",
            "gst": "-",
            "id": 91,
            "image": "https://www.sgxacademy.com/wp-content/uploads/2018/09/shutterstock_114054154_211x1361.jpg",
            "isAvailable": "Available",
            "price": "S$160",
            "title": "Economic Indicators \u2013 An Introduction, Inflation & Employment and...",
            "type": "Beginner",
            "url": "https://www.sgxacademy.com/event/economic-indicators-an-introduction-inflation-employment-and-national-accounts-2/"
        },
        {
            "currency": "S$",
            "gst": "-",
            "id": 92,
            "image": "https://www.sgxacademy.com/wp-content/uploads/2018/12/invest.jpg",
            "isAvailable": "Available",
            "price": "S$160",
            "title": "Dark Pools, Equity Markets Introduction & Issuing",
            "type": "Intermediate",
            "url": "https://www.sgxacademy.com/event/dark-pools-equity-markets-introduction-issuing/"
        },
        {
            "currency": "S$",
            "gst": "-",
            "id": 93,
            "image": "https://www.sgxacademy.com/wp-content/uploads/2018/12/book.jpg",
            "isAvailable": "Available",
            "price": "S$160",
            "title": "An Introduction to Convertibles and Contingent Convertibles",
            "type": "Beginner",
            "url": "https://www.sgxacademy.com/event/an-introduction-to-convertibles-and-contingent-convertibles/"
        },
        {
            "currency": "S$",
            "gst": "-",
            "id": 94,
            "image": "https://www.sgxacademy.com/wp-content/uploads/2018/12/book.jpg",
            "isAvailable": "Available",
            "price": "S$160",
            "title": "Structured Products \u2013 An Introduction, Major Types and Valuation...",
            "type": "Intermediate",
            "url": "https://www.sgxacademy.com/event/structured-products-an-introduction-major-types-and-valuation-risks/"
        },
        {
            "currency": "S$",
            "gst": "-",
            "id": 95,
            "image": "https://www.sgxacademy.com/wp-content/uploads/2018/09/shutterstock_79462060_211x1361.jpg",
            "isAvailable": "Available",
            "price": "S$160",
            "title": "An Introduction to Emerging Markets & Investment",
            "type": "Beginner",
            "url": "https://www.sgxacademy.com/event/an-introduction-to-emerging-markets-investment/"
        },
        {
            "gst": "-",
            "id": 96,
            "image": "https://www.sgxacademy.com/wp-content/uploads/2018/09/course-icon-beginner1.jpg",
            "isAvailable": "Available",
            "price": "FOC",
            "title": "CBOE Options Institute at SGX: Beginner Module",
            "type": "Beginner",
            "url": "https://www.sgxacademy.com/event/cboe-options-institute-at-sgx-beginner-module-2/"
        },
        {
            "gst": "-",
            "id": 97,
            "image": "https://www.sgxacademy.com/wp-content/uploads/2018/10/cboe.jpg",
            "isAvailable": "Available",
            "price": "FOC",
            "title": "CBOE Options Institute at SGX: Intermediate Module",
            "type": "Intermediate",
            "url": "https://www.sgxacademy.com/event/cboe-options-institute-at-sgx-intermediate-module/"
        },
        {
            "gst": "-",
            "id": 98,
            "image": "https://www.sgxacademy.com/wp-content/uploads/2018/10/course-icon-professional.jpg",
            "isAvailable": "Available",
            "price": "FOC",
            "title": "CBOE Options Institute at SGX: Advanced Module",
            "type": "Professional",
            "url": "https://www.sgxacademy.com/event/cboe-options-institute-at-sgx-advanced-module/"
        }
    ],
    "GetDateTime": "2018-12-26 12:46:41.006218",
    "RecordCount": 98
}